LICENSE
setup.cfg
setup.py
weightbridge/__init__.py
weightbridge/format.py
weightbridge/matcher.py
weightbridge/state.py
weightbridge/tree.py
weightbridge.egg-info/PKG-INFO
weightbridge.egg-info/SOURCES.txt
weightbridge.egg-info/dependency_links.txt
weightbridge.egg-info/requires.txt
weightbridge.egg-info/top_level.txt
weightbridge/matchers/__init__.py
weightbridge/matchers/base.py
weightbridge/matchers/match_by_paired_children.py
weightbridge/matchers/match_by_paired_parents.py
weightbridge/matchers/match_by_paired_predecessors.py
weightbridge/matchers/match_by_paired_prefixes.py
weightbridge/matchers/match_by_structured_shapes.py
weightbridge/matchers/match_equivalent_hardcoded_leafs.py
weightbridge/matchers/match_identical_names.py
weightbridge/matchers/match_known_paired_number_regex.py
weightbridge/matchers/match_number_regex.py
weightbridge/matchers/match_passed_hints.py
weightbridge/matchers/match_unique_leafs.py
weightbridge/matchers/util.py